tac1/__init__.py
tac1/tac1.py
tac1-0.7.0.dist-info/LICENSE.txt
tac1-0.7.0.dist-info/METADATA
tac1-0.7.0.dist-info/WHEEL
tac1-0.7.0.dist-info/entry_points.txt
tac1-0.7.0.dist-info/top_level.txt
tac1-0.7.0.dist-info/RECORD
