Metadata-Version: 2.1
Name: tac1
Version: 0.7.0
Summary: Simple note taking app
Home-page: https://github.com/JayZar21/tac1_py
Author: Gianluca Romanin
Author-email: romaninz@gmail.com
License: UNKNOWN
Platform: UNKNOWN
Classifier: Programming Language :: Python :: 3
Classifier: License :: OSI Approved :: MIT License
Classifier: Operating System :: OS Independent
